puresnet/S_parser.py
puresnet/__init__.py
puresnet/atom.py
puresnet/dataset.py
puresnet/error.py
puresnet/featurizer.py
puresnet/model.py
puresnet/predict.py
puresnet/residue_h.py
puresnet/resnet.py
puresnet/sparse.py
puresnet/train.py
puresnet/data/model90 70210.pt
puresnet/data/training_data.npy
puresnet/data/validation_data.npy
puresnet-0.1.dist-info/LICENSE.txt
puresnet-0.1.dist-info/METADATA
puresnet-0.1.dist-info/WHEEL
puresnet-0.1.dist-info/top_level.txt
puresnet-0.1.dist-info/RECORD
