Metadata-Version: 2.1
Name: puresnet
Version: 0.1
Summary: PUResNetV2.0 Prediction of Protein Ligand Binding Sites
License: MIT License
License-File: LICENSE.txt
Requires-Dist: numpy
